README.rst
liquer.py
setup.py
liquer.egg-info/PKG-INFO
liquer.egg-info/SOURCES.txt
liquer.egg-info/dependency_links.txt
liquer.egg-info/top_level.txt