Metadata-Version: 1.0
Name: liquer
Version: 0.0.3
Summary: Query your objects for two cents!
Home-page: https://github.com/kadirpekel/liquer
Author: Kadir Pekel
Author-email: kadirpekel@gmail.com
License: UNKNOWN
Platform: UNKNOWN
